scs/__init__.py
scs/supercoeffs.py
scs/utils_opt.py
scs_kc-0.1.2.dist-info/METADATA
scs_kc-0.1.2.dist-info/WHEEL
scs_kc-0.1.2.dist-info/top_level.txt
scs_kc-0.1.2.dist-info/RECORD
