Metadata-Version: 2.4
Name: scs-kc
Version: 0.1.2
Summary: Package for Kerr-cat optimization routine with super coefficients
Author: Roman Baskov
Requires-Python: >=3.10
Dynamic: requires-python
